{
  "project_info": {
    "project_number": "269855069996",
    "project_id": "progettopwm-d0d07",
    "storage_bucket": "progettopwm-d0d07.appspot.com"
  },
  "client": [
    {
      "client_info": {
        "mobilesdk_app_id": "1:269855069996:android:a78b3bb3aa61f5c82ffe89",
        "android_client_info": {
          "package_name": "com.example.progettopwm"
        }
      },
      "oauth_client": [
        {
          "client_id": "269855069996-1jmcrp938vmneho6s4schhnnguuqvvun.apps.googleusercontent.com",
          "client_type": 1,
          "android_info": {
            "package_name": "com.example.progettopwm",
            "certificate_hash": "55d82a65259609c1ba0442f5c5757c5f93c8d63e"
          }
        },
        {
          "client_id": "269855069996-5l8aqsmk4g130so8tanhqpsgj4bront5.apps.googleusercontent.com",
          "client_type": 3
        }
      ],
      "api_key": [
        {
          "current_key": "AIzaSyAsAxZL46eqoMRzj6T2Z93bSm5hMFnoVLA"
        }
      ],
      "services": {
        "appinvite_service": {
          "other_platform_oauth_client": [
            {
              "client_id": "269855069996-5l8aqsmk4g130so8tanhqpsgj4bront5.apps.googleusercontent.com",
              "client_type": 3
            }
          ]
        }
      }
    }
  ],
  "configuration_version": "1"
}